louati_mahdi_analytics/__init__.py
louati_mahdi_analytics/_reporter.py
louati_mahdi_analytics/_style.py
louati_mahdi_analytics/base.py
louati_mahdi_analytics/causal.py
louati_mahdi_analytics/cli.py
louati_mahdi_analytics/sql_parser.py
louati_mahdi_analytics/stats.py
louati_mahdi_analytics/visuals.py
louati_mahdi_analytics-1.0.2.dist-info/METADATA
louati_mahdi_analytics-1.0.2.dist-info/WHEEL
louati_mahdi_analytics-1.0.2.dist-info/entry_points.txt
louati_mahdi_analytics-1.0.2.dist-info/top_level.txt
louati_mahdi_analytics-1.0.2.dist-info/RECORD
