Metadata-Version: 2.4
Name: louati-mahdi-analytics
Version: 1.0.2
Summary: A powerful SQL-like query language for Data, Stats, Causal AI, and Plotly Viz.
Home-page: https://github.com/mahdi123-tech
Author: Louati Mahdi
Author-email: louatimahdi390@gmail.com
Classifier: Programming Language :: Python :: 3
Classifier: License :: OSI Approved :: MIT License
Classifier: Operating System :: OS Independent
Requires-Python: >=3.6
Requires-Dist: pandas
Requires-Dist: numpy
Requires-Dist: tabulate
Requires-Dist: plotly
Requires-Dist: scipy
Requires-Dist: statsmodels
Requires-Dist: sqlparse
Requires-Dist: qrcode[pil]
Requires-Dist: fpdf2
Requires-Dist: kaleido
Dynamic: author
Dynamic: author-email
Dynamic: classifier
Dynamic: description
Dynamic: description-content-type
Dynamic: home-page
Dynamic: requires-dist
Dynamic: requires-python
Dynamic: summary
